{
  "id": "22b9c2be268c44c9b67e2af8600acf35",
  "system_id": "d38a20c38e09938c46f56324bde9d52a98553f0a",
  "start_time": "2025-08-07T02:49:37.696507+00:00",
  "end_time": "2025-08-07T02:50:03.212088+00:00",
  "targets": [],
  "force": false,
  "dvc_args": [],
  "status": "completed",
  "stages": {
    "_check-env-main": {
      "start_time": "2025-08-07T02:49:37.919000",
      "end_time": "2025-08-07T02:49:39.027000",
      "status": "completed"
    },
    "get-data": {
      "start_time": "2025-08-07T02:49:39.027000",
      "end_time": "2025-08-07T02:49:54.228000",
      "status": "completed"
    },
    "plot-weekly-dists": {
      "start_time": "2025-08-07T02:49:54.228000",
      "end_time": "2025-08-07T02:49:58.986000",
      "status": "completed"
    },
    "plot-weekly-energy": {
      "start_time": "2025-08-07T02:49:58.986000"
    }
  },
  "git_rev": "4ba3360882782035325ca0e8d0055c145a2311d7",
  "git_branch": "main",
  "git_changed_files_before": [],
  "git_staged_files_before": [],
  "git_untracked_files_before": [
    ".calkit/systems/d38a20c38e09938c46f56324bde9d52a98553f0a.json"
  ],
  "git_changed_files_after": [
    "figures/dists-latest-week.json",
    "figures/weekly-dists-24-weeks.json",
    "figures/weekly-energy.json"
  ],
  "git_staged_files_after": [
    "dvc.lock"
  ],
  "git_untracked_files_after": [
    ".calkit/systems/d38a20c38e09938c46f56324bde9d52a98553f0a.json",
    "data/activities/15370959023.json",
    "data/activities/15370959024.json"
  ],
  "dvc_status_before": {
    "_check-env-main": [
      "always changed"
    ],
    "get-data": [
      "always changed"
    ]
  },
  "dvc_data_status_before": {
    "not_in_cache": [],
    "not_in_remote": [],
    "committed": {},
    "uncommitted": {},
    "untracked": [],
    "unchanged": [
      "data/timeseries/"
    ]
  },
  "dvc_status_after": {
    "_check-env-main": [
      "always changed"
    ],
    "get-data": [
      "always changed"
    ]
  },
  "dvc_data_status_after": {
    "not_in_cache": [],
    "not_in_remote": [],
    "committed": {
      "modified": [
        "data/timeseries/"
      ]
    },
    "uncommitted": {},
    "untracked": [],
    "unchanged": []
  }
}