{"id":10744207883,"achievement_count":10,"athlete":{"id":12343101,"resource_state":1},"athlete_count":1,"average_speed":4.793,"average_watts":121.6,"comment_count":0,"commute":false,"device_watts":true,"distance":47873.6,"elapsed_time":12150,"elev_high":381.6,"elev_low":9.8,"end_latlng":[37.98,-122.59],"external_id":"garmin_ping_320599949004","flagged":false,"gear_id":"b8359472","has_kudoed":false,"hide_from_home":null,"kilojoules":1219.5,"kudos_count":14,"manual":false,"map":{"id":"a10744207883","polyline":null,"summary_polyline":"{dyfFnqfkVaCGeCeEaD_BsDcDUkBmAoArBsEzAUZoDhB}@pCgHs@aIy@qBdBcTSqDlA{BrCoA|D{HtDgEU}H|EwLlCy@KyFrCoYvD}GpLaCzDtOjBa@zBgB}BwMdPqDfBzClI{DvCf@zHuCkHlCyDa@yBzAtC{ApCj@bDq@rWyJVi@iAoHfFiGpf@{TnB_DzRcIn@fJdEnLj@hEo@jk@`ArFs@lB}CPqA{@yB|B|HhEd@rEc@Pi@yAeJUiAy@yCz@fAfB~AlKxMtE`DvG~Dn@~JuDrC}CrDJfCaFzEs@tByGhJoAh@oD{@yAyC}@?wC{AoBDiGyC_A`@{CcAsC~ARp@dBvAYpAz@tAgCt@lAUbE~FjDvApD`Ci@AeBVaC`A}FpC}CfEvA|@{C~AyAfBbA`CmAdD~AtBcBp@gClCM`A{DdB@fAoFlCcAhAeCxACkATs@bCqBpAtKaD`AtEpBfDLcClCWz@oAjAvClCq@Z{ChCzB~BRvAuCbBs@oB|FgNpEqApDaJtAwAzBiFJmHrC@{@rCmDaBqDAuAwB~DeHrJkInAWnEkF`DjBxHd@dIzBrA~C_Ej@jC|C]xCkGtD}@lBfB`DcCbAR|@hC`Bx@q@~DRpBvCaApBz@bCyB|@hFc@bEfBtC~DwGjCPrA}CjCbEbCe@x@lBQjBaDhEnBv@hAnJdCm@`Bl@vCxBXnDx@d@\\k@K{BkCwHTw@v@Bl@dEfE|F_BnC@dArKvCM~DeAnAo@hEvBbA~@jChJ\\nAuArLoAhFuF`IUpXqWfDqOzCmClGY`GoFz@iFhBsBlAsFu@sEpB{HxBaAxDRhAoDxIkNpIyChDcEOu@oFQqHbFcIpAcFIaCyAiAdAsFkAkD~@{AcKjFkJfAqEu@oLwA|As@zIgDAgCrF`@vAiEp@CrD_Cx@{DdEU|Ah@rBaCdBPlEg@jB]KVqBgA{FdAiJxAwHjBk@lCmG{@iHxAoEaA_JoG}KAkHvI{OtEmMPmYrPee@xAsLkK_DyCsCiCs@eDjB}DVuAdCiEpCoCwDqDnAwHFwAoEeE~BmAqDuDOqD}DaGtC{HeGyBxCRxDeBrFkIjAq@|GeCy@aBdAoBoBmDxAUnCu@L{DeBwB_GgBY}@hCoDb@gRrR}DpJkIjDkF^a\\}FaCJwMpO{C`GuIvFmGvMgHbIeQz`@yKbAuSfJ_CpDif@fTqFrGx@xI{W~JoCl@_Dm@mIbEiBiC}@CiS`FaPdBuEbIuC~YJlFaCh@_FjLF`JiJtNiDjBkVhb@mE~Sk@vPnH`E`CpFjFbDdC{FfGvE|BgB"},"max_speed":14.222,"max_watts":380,"moving_time":9988,"name":"FR FR","photo_count":0,"private":false,"sport_type":"Ride","start_date":"2024-02-11T20:42:12Z","start_date_local":"2024-02-11T12:42:12Z","start_latlng":[37.98,-122.59],"timezone":"(GMT-08:00) America/Los_Angeles","total_elevation_gain":899.0,"total_photo_count":2,"trainer":false,"type":"Ride","upload_id":11488886186,"upload_id_str":"11488886186","weighted_average_watts":148,"workout_type":10,"utc_offset":-28800.0,"location_city":null,"location_state":null,"location_country":"United States","pr_count":1,"suffer_score":53,"has_heartrate":true,"average_heartrate":112.5,"max_heartrate":154,"average_cadence":75.3,"from_accepted_tag":false,"visibility":"everyone"}