{"id":11497422516,"achievement_count":42,"athlete":{"id":12343101,"resource_state":1},"athlete_count":1,"average_speed":5.664,"average_watts":150.9,"comment_count":0,"commute":false,"device_watts":true,"distance":71163.1,"elapsed_time":13360,"elev_high":769.8,"elev_low":6.2,"end_latlng":[37.98,-122.59],"external_id":"garmin_ping_343116439039","flagged":false,"gear_id":"b8359472","has_kudoed":false,"hide_from_home":null,"kilojoules":1897.4,"kudos_count":10,"manual":false,"map":{"id":"a11497422516","polyline":null,"summary_polyline":"}nxfFvkfkV~FRoNxIyHk@_EtEcDH~Gj@lBvJlGfJjXdJtKhPCjc@i@nPcCrEs@~SoC|Bl@jPiBpDdJjG|GzHy@hHoExDhAvEuAdHhG{F`GdHpDgIfIvBbFkE~Uv@`AtEyQ|I}FtJkBxIpQuMnG~Cm@~KnVcRxTrFzE~JoBnFfCtD@zD}CfK|IgBpC_IbD}@`BkHrFuAt@oF|BhCnG[yBvFt@jG`MeIdBPtBdD`IqGxC?JpDzEv@OfHjBrEaBvD`DjAnAxEdY}BwBBuArDeHf@HxSdEfH_FlIrBbCF~GoFtLpDbH^pHcBrAcB~NrJaImAfFuCjAe@`FsNlGtLCmB~DpAxF_D~@hAlEkGcAcE~C?~GeHjCbEtCdE|J_AbEsIsBtAdHo@jCpDbBOzH`F~JG~FaC`CuFs@kAvFaKyAyDdBrErGrHxCHtCnE`@t@dDdKnHUbH`Dw@`DvKrDrAAtCxCzAhCdIlAIm@cF`N~Gp@|OqHiBi@rLaC|B`FpAz@lNjB~BjGkQWkKzDyGh@kKtJeEAyVpB_HnL}BrJsIxCqHMmMrAsEnLwGvHmO`OcHhDiLt[qYjAmJxHkJnLi_@jImGpAyLdLuHbFaL~Zu^tCw]dLqEyHsLyITbF}JrCBdKwEhFuLgFfBzAoFzHcGrHwNRyLwKrGdCyJcEaI\\gJ_IMnAiGi@cIoFwFFsFgKyA{DqIsC~@`@qEqB_DmLg@oJzE^wFnD_Eu@uEdByC^aKaD}@rA~CoEpEiBvDIlCsEhAn@xEmF~KfDpHc@tDfMJK`BmHxBkIuCuBVoEoHgEOoGaHeFpBaGmFqD}NqW_IsDwG]kFiGaCaHuM~A_LoCgFhAiK_Qs@cIaOxBaNjIeOoCkA_@cDaKu@q@gFmDoCtIeOb@qI_BwCYvQeG`KzDbEr@xEvJj@ZbDjCdAgI|NcChIRbE|H`NvPj@gAvKlC`F{AhLtG`MlGzBb@vFxDbHdWnHzDhOrF`FhFoBbF`Eb@tGvGhO[tQuGjIkD~\\qG_EmHvJiKdE_AfG{MA}G~FgEjRuSvc@TfGmx@ne@_KbXvAfM{HrWcMtHwGoAkEbBpEwEjGaAf@gFfC_AjByF_KvHbBcNfBqAYkHsDeHnFeMAuGuBwDfCgApAyE_EeHOcSpJoFfCKaYrB{A{E{CcA|AeDiBgFTyG_FkAKoDoCMgJ~G{AeD{A]yMfIc@uFtBcGgG^kCqCw@pFkF~AeG|ImCvHgJpBfDyOkCiEfBiHyEwIkT{FcW`R|@sKiGmDwQ`NxA_IlGiKzQcJcAwE}U}@kFrEqI_CmDjIuFiHqGvF|AqGgAaFdEeDbAkHiMuJyDkFhByCo@wPnCwBj@kSjCeFd@mPBsc@mKmPoXeJaIeMk@cGgCiAfCsD"},"max_speed":17.106,"max_watts":405,"moving_time":12563,"name":"Fresh rubbah","photo_count":0,"private":false,"sport_type":"Ride","start_date":"2024-05-25T19:33:02Z","start_date_local":"2024-05-25T12:33:02Z","start_latlng":[37.98,-122.59],"timezone":"(GMT-08:00) America/Los_Angeles","total_elevation_gain":1851.0,"total_photo_count":2,"trainer":false,"type":"Ride","upload_id":12274230662,"upload_id_str":"12274230662","weighted_average_watts":193,"workout_type":10,"utc_offset":-25200.0,"location_city":null,"location_state":null,"location_country":"United States","pr_count":18,"suffer_score":204,"has_heartrate":true,"average_heartrate":130.9,"max_heartrate":166,"average_cadence":86.5,"from_accepted_tag":false,"visibility":"everyone"}