{"id":12047407023,"achievement_count":1,"athlete":{"id":12343101,"resource_state":1},"athlete_count":1,"average_speed":4.367,"average_watts":124.8,"comment_count":0,"commute":false,"device_watts":false,"distance":20513.1,"elapsed_time":6837,"elev_high":172.6,"elev_low":19.0,"end_latlng":[37.98,-122.59],"external_id":"garmin_ping_359568359618","flagged":false,"gear_id":"b5121504","has_kudoed":false,"hide_from_home":null,"kilojoules":586.0,"kudos_count":8,"manual":false,"map":{"id":"a12047407023","polyline":null,"summary_polyline":"udyfFlqfkVsB@]QmAiBa@oAmDmB_@gAUU{Aa@m@q@Ma@Dq@qA}@BYxAiC`@eArAOHYIcAd@_BX[hA_@^_Bd@c@dAyCo@_E?}B{@sB?]P{AAaCl@}Bf@iHC_BSaAD]p@qAr@{@nBu@j@m@zDyHrCuCJw@[_DAqBFY~EcLl@S|@AT[KqFfCeWP{AbA}AC[s@YdBoG?y@IC@cCJ{AXu^GyF]SsC\\[Ge@q@w@gCOIjArDh@\\j@QFWMsBNe@MR?h@RtBNLrAK\\ZDzEQpWRZhABNLhAhCDpBIdDIPqBGURe@vBSX?j@f@n@mCpEAr@wCrXLbFWTsABSNiEvJUz@E`A@xAV`CIp@oCzC{EdJkCjAe@j@s@lBLt@@~Be@`Hm@dCBpBMhBz@|BE|Ap@fEEf@}@lCc@`@WtAKP_ALYPo@`BCVPp@EXQLcAJo@zA{@jAWp@Bb@fAj@?|@FTn@x@zAd@XXJf@TXlDfBb@zA~AlB|BAvAy@d@bAf@\\r@@lAUh@YjDsEBKEC?AFHgDdEe@b@y@XqAFYQm@sAKEwAbAwBB[UsAiBw@Ha@f@u@_@QBeAjAqEwCiA{DKUOAeAdCgBc@MHY~@aBS_@Jk@f@}@QuAdCk@l@}EfBIRAhAk@\\o@hAmDzNwCm@{A`@{BeA_AOkBLuAr@s@v@c@~@_@dCO`@iA`@M\\MtCUx@aB`CkB~A{@tBm@z@wIfJaCpBuEpH]|@i@rC_ABQrE^|GElAgCxH}@nF_D|G_AfF_AvB}AzA_Bl@aHNeA\\sDbDwAhBeBh@k@d@sAnD_Az@sATwB_@aADyFbB{@hAII?Oxn@at@D[EaBuAgEMqA_BkAm@DQ{@}@yAaDaCY?u@`AeAkBq@Q_BZc@h@u@NsAt@sADWE]_@a@s@TFj@Dh@Zp@I^]r@_D?i@HQV?EOf@QhDh@fF@lAWp@@bChAnChChEb@xBk@`@u@dAsDp@kE^}@b@UhCVJVIpAJDHKb@sG`AaEdBqCvAoAnGwC`A}@bBqClBeE~@oCQg@e@DWx@SD|@]E_@HCZRq@zABTPE~DuIn@w@~SkN~AkBhGcCbDaAxCwA`AyAp@eC^ILOTwAn@JbGxCpA`Ef@r@vAp@tArAxDpArArBl@ZjEDTUNm@hBkB"},"max_speed":10.894,"max_watts":null,"moving_time":4697,"name":"Amp","photo_count":0,"private":false,"sport_type":"Ride","start_date":"2024-08-02T21:55:22Z","start_date_local":"2024-08-02T14:55:22Z","start_latlng":[37.98,-122.59],"timezone":"(GMT-08:00) America/Los_Angeles","total_elevation_gain":260.0,"total_photo_count":0,"trainer":false,"type":"Ride","upload_id":12842401052,"upload_id_str":"12842401052","weighted_average_watts":null,"workout_type":10,"utc_offset":-25200.0,"location_city":null,"location_state":null,"location_country":"United States","pr_count":0,"suffer_score":19,"has_heartrate":true,"average_heartrate":109.3,"max_heartrate":138,"average_cadence":null,"from_accepted_tag":false,"visibility":"everyone"}