{"id":12863722249,"achievement_count":1,"athlete":{"id":12343101,"resource_state":1},"athlete_count":1,"average_speed":5.348,"average_watts":141.4,"comment_count":0,"commute":false,"device_watts":true,"distance":69940.3,"elapsed_time":14791,"elev_high":768.2,"elev_low":12.2,"end_latlng":[37.98,-122.59],"external_id":"garmin_ping_384595590019","flagged":false,"gear_id":"b8359472","has_kudoed":false,"hide_from_home":null,"kilojoules":1851.5,"kudos_count":11,"manual":false,"map":{"id":"a12863722249","polyline":null,"summary_polyline":"cbyfFxvfkVgCrDhC~@pAvIzGtJdXxI|KjQIrb@o@pQ{BxDq@vSqCzBn@hPkBpDbSzQy@dHkEtDdAnEwAfHhG}FtFlHpDoIfI`ChFoEfVr@jAjEuQ`JiG~JcBbJpQ_NbG|Cu@bL|VcRnTvFrEfIaBfHnC|DcDvP~IoBfCeIbDw@~AkHtFiAr@yFfCnCpGSsBhF\\rGtMkI~ATfBhDxMyGXtDbF`AOpGjBlFeB`DbD|AvAnE~X_CwBHyApDeH`@DtSjErHeFjItCbGgGxQpDtG`@zHiBrAaBzNr@oCfIqDsAfFsCfAi@lFkBYoCpAsFbFvFgBlFrAfM_H|HoXsA_LhK}XxXoMx^cW_@{F`Tod@zDwQvHiGnM@h@wFvKoEdHsJfGjErDg]xG_I^qRoGwNs@uHsF{DmEvBsFuE}DqOkWwHsD}Gc@yF{FkBiHqM|AmLmCoF`AmK{Pg@_I{O|H`PzPn@iAjKnCnF{AhL`HhMnGdCPzEvDbHrWzHlE`PnFnExEyBnGfHrEXbEfHhI~B|LiCU{BoLLd@aDqD_HrFaMq@wEhEy@lB_EFiCtEoEkAiDvC`Ae@nJiB~Cx@bFuDhDe@zFnKyElKn@vB`Dg@jE`Du@pDnI~JhA?pFpF`Gn@zHkAzGlHSUxJbEvIeChJrF}@pDgE_@hLoHnNwHzF}AlG~EiBkFjLuJhEsCAqF`KlII`F|EvAxFyHnBfChJtDTuB|C{B[mAlGcDWiH|Q_TbTcF`LoLfImApLiIdGoLt_@sHxIkArJy[tY_D~KwNvG{HrOqMxHs@tSkC|GyJ|IgL~AeCrIFfVwJ~Dk@zKwDlGXlKeGjQcBqBaA_O{EcA|BaCl@sLfH~Bo@qPgNmHh@nFgA@}B{HaDwACgDoDuA{CqK_D`AXoGgKqHs@kDoFqEmHmCoEmGlDcBlK|AfA_GbGv@~BeCFyFaFsJFyIgDiAj@_CaBeI~I`C|@kEeEiKcE_CbHiCAwGrDuDrGtAaA{EbDw@qA}FzBaEeMGlN}Fj@qFhCw@~AgFaKjHfB}MhB_B[{HqDyG`G}QmCgHjCuApAcFeEoHQgR|JqF`CEaYnBwAuE{CaAzA_EeBuEP_H{E}@OsDqCMuJ~GiDeEyMhIa@uFvBgGwGT_CeCq@lFkFtAkGdJcCnHoJzBdDsOkCqEdBiHoEoIwTaGuVfRp@eL}FaDyQjNvAmIlGeKtQ_J_A{EgVy@cFpE{H_C}DhIkGeH}FzFvA}GcA_FhEgDx@qH_SgQlB{DmAwE\\oIhCsBp@uSdCmEj@uPDcc@cLqQcX}IgJyTaCgAqAiF{FaFuF[aDwGmFgCH_FyCm@lCuUsCfUrC`AA`FxO`OfFcBjFxB"},"max_speed":15.7,"max_watts":404,"moving_time":13078,"name":"The soft thing about soft things","photo_count":0,"private":false,"sport_type":"Ride","start_date":"2024-11-09T20:06:36Z","start_date_local":"2024-11-09T12:06:36Z","start_latlng":[37.98,-122.59],"timezone":"(GMT-08:00) America/Los_Angeles","total_elevation_gain":1742.0,"total_photo_count":5,"trainer":false,"type":"Ride","upload_id":13716862488,"upload_id_str":"13716862488","weighted_average_watts":168,"workout_type":null,"utc_offset":-28800.0,"location_city":null,"location_state":null,"location_country":"United States","pr_count":0,"suffer_score":194,"has_heartrate":true,"average_heartrate":129.6,"max_heartrate":156,"average_cadence":85.0,"from_accepted_tag":false,"visibility":"everyone"}