{"id":13763514081,"achievement_count":0,"athlete":{"id":12343101,"resource_state":1},"athlete_count":1,"average_speed":4.905,"average_watts":127.4,"comment_count":0,"commute":false,"device_watts":true,"distance":15833.0,"elapsed_time":3932,"elev_high":336.2,"elev_low":37.8,"end_latlng":[37.98,-122.59],"external_id":"garmin_ping_415513704565","flagged":false,"gear_id":"b8359472","has_kudoed":false,"hide_from_home":null,"kilojoules":411.6,"kudos_count":3,"manual":false,"map":{"id":"a13763514081","polyline":null,"summary_polyline":"sayfFnvfkVaCvBKpA~AX^XFPGx@Bh@Vn@LpAl@`B^j@|A|Ap@rA~@|@j@zAn@RjAQpALr@d@d@`AXT`DlA`CJbB|AbB`@rFrFtAdDTjAf@l@L`@JfBKlCRzAi@rCIrA@pB[fDH|D`@nA@XIb@m@x@O|@Z|COdCR`BCz@Y~@kAx@Wt@QfGU`BLhBU|Dg@r@kA^]r@Ab@\\~BIb@i@pACx@JhAn@fANr@C\\OZiAnAMt@D^LV`B|@dAnB\\JhA@x@XnDrExAx@\\x@C~A]|B[bAa@h@wClBQV@j@t@lBLfAOnAmAzBEh@D`@d@Vf@ST[`@kAfAw@b@_Ad@WzBjA`@t@TlAd@dARNR?Zc@ToAv@YLULwBFYPOp@Dv@|@X?jAWvAhAx@B`@Uh@yAn@}@xAc@j@Hf@^dAUj@?lAb@lAM~Dt@tBk@v@?h@`@v@nB?j@Ud@uCzBc@PqANgBnAmBP_Ad@s@p@g@xAaArBoBtBk@~@e@fC}@xBBnARTL?AMWSC{@n@cBn@}Ch@{@jBoBbAmBn@mBj@m@d@WjAWx@Af@Wn@q@lB]tDmCVk@As@u@gBU[[Ki@AeCh@yDq@oAHiB_@oAXi@]wAAw@Vy@nA[dA_@Ty@EqAeAkBT_AcAq@BQ^G|AOl@_A\\UrAW`@OBYSmAuD{AmAg@Oe@Ju@pA{@j@{@jBa@N]MI_@D]hA_CRsAKgAw@gBEk@T_@rBoA~@aA\\eA^_C?iBUo@aBeAaDiE}@c@qA?_@Ms@}AmBiASm@Ls@dAmATq@Es@aAkCA]Fw@h@aBCu@UiA@q@Rc@zAk@Xe@^gEO{BNiAXaHVi@bAu@Vk@Hq@SsBLyC[iCLw@n@y@Pq@AYc@yAKoEVaCDmDl@mDQoBHwBGsBIYk@}@eBcFsF_GeBe@iB}AeCQcDmAaA{As@c@y@KyAPm@Km@{AaA}@o@oAcBgB[g@m@{AGm@c@uAD_B]i@mCk@y@BoCSkBcCeDmAaByAaBw@s@eAo@_C[m@sG}C[YI[r@}N^gDrAcFJcAEo@D]\\TM?BJSDc@tCgAxDa@hDKfDDPTJzBNDROpDFZdF`CT^rAhEfExCTAx@kAHAhGxEXMzA{A"},"max_speed":15.14,"max_watts":271,"moving_time":3228,"name":"Afternoon Ride","photo_count":0,"private":false,"sport_type":"Ride","start_date":"2025-03-01T22:07:55Z","start_date_local":"2025-03-01T14:07:55Z","start_latlng":[37.98,-122.59],"timezone":"(GMT-08:00) America/Los_Angeles","total_elevation_gain":367.0,"total_photo_count":0,"trainer":false,"type":"Ride","upload_id":14689079238,"upload_id_str":"14689079238","weighted_average_watts":152,"workout_type":null,"utc_offset":-28800.0,"location_city":null,"location_state":null,"location_country":"United States","pr_count":0,"suffer_score":9,"has_heartrate":true,"average_heartrate":103.8,"max_heartrate":124,"average_cadence":80.4,"from_accepted_tag":false,"visibility":"everyone"}