{"id":14035441585,"achievement_count":10,"athlete":{"id":12343101,"resource_state":1},"athlete_count":1,"average_speed":5.06,"average_watts":136.4,"comment_count":0,"commute":false,"device_watts":false,"distance":24911.9,"elapsed_time":21723,"elev_high":65.8,"elev_low":7.6,"end_latlng":[37.98,-122.59],"external_id":"garmin_ping_424400339306","flagged":false,"gear_id":"b5121504","has_kudoed":false,"hide_from_home":null,"kilojoules":671.6,"kudos_count":9,"manual":false,"map":{"id":"a14035441585","polyline":null,"summary_polyline":"idyfFfqfkVwC@y@eAcAaCeD}A_@aA]c@eAOs@m@Ue@?_A_Ak@Og@zAuC\\cA`BYBSSu@d@gB^_@fAUXqAp@w@`AmC@[q@gEHsAC[_AiBRsCIeADe@h@uBh@kHCoBQy@DSl@uAt@u@dCiAxDyHlD{DLo@YoC?uC`AqCdDcHtB]DUM}EtC{YtCqEt@iBz@c@rDQpBm@jEM`Cy@jQ{DTPl@dCTJjCm@lEwCbBf@l@FfCi@nGuCfPoFJg@kAaHBU|AqAnCqDt@SbEsBdCgBtZiMvAkClD_BbPwGpFOlAOz@c@f@q@vLqWbBoE`CkD~BcBz@kAfBuDlBmFE_@Ua@iDoDsE{HLq@pDcFxAyDb@gCRyGYmCcBgEcBcBaAwA]oASsAFwGRyBp@cDdAwBlAsAvBaGpDkMRiA?q@kCiCSg@Eu@Jw@RWlEuCJs@KyAUiB_@mAoDuDuD{GKo@Bc@d@y@Lk@IY}@uAaAGMSW{B_AoCoEqJb@c@`AkAL?mAvAsCcAKsAMu@p@mDo@w@oA?mA{@m@f@cBtDFDdG_Mr@i@Hk@SeAgA?WYa@_A_AsDcBsCCg@SYZj@GVRd@`@d@?Mc@QJ@G@U{AYCfApAtC|Ip@h@p@GVlAJPnAj@OhAf@n@J`AkBjDm@nCEb@Ph@FlAxCfAfAuAM@cBjBbC`FxBjFn@hEpA?x@hBEh@a@p@Kn@Nv@jErHjCbCf@jAVvALlCG`@qEbD]z@FhAJRzAlBp@VHTQfBsExOqApDQ\\gCdDm@|B_@`DQpFZ|CdAfCxBvBdBpEN`AFnAa@vIcBxEqEpGc@~AgFnAmAj@cAbAm@dAk@fB_BrTY|Ai@`Aq@j@_QbFq@nAYTiAL{@QKZmB]g@Fa@\\Yz@@|E{@zDYvCFtBe@`D}DlFwCtBaHxCo@@iBm@_BTm@`AiE~DgDxEObAyAvBOf@qCfClAzHIRiPtFmH`DaBXuBo@o@FyDlCeCn@QG_@gAq@y@eAA{OnDcBp@mEPwAd@iBVwBBs@h@k@zAoBtCc@~@uCpZPvDG`@cBRWRcFjLC`CXbDKp@oBvBy@fAaE`IqBr@i@b@eAvBP|D_@xGm@rBGfAD~@UfBP|@^n@Jl@G~@t@`FCPy@nCs@bAO|@cBr@o@~ALhAEVMNgAFk@vAwA`C@ZNPp@VJT?|@h@x@lBr@h@rAvDnBt@lBfAvAzB?"},"max_speed":10.28,"max_watts":null,"moving_time":4923,"name":"WL","photo_count":0,"private":false,"sport_type":"Ride","start_date":"2025-03-30T22:08:05Z","start_date_local":"2025-03-30T15:08:05Z","start_latlng":[37.98,-122.59],"timezone":"(GMT-08:00) America/Los_Angeles","total_elevation_gain":173.0,"total_photo_count":0,"trainer":false,"type":"Ride","upload_id":14982309953,"upload_id_str":"14982309953","weighted_average_watts":null,"workout_type":10,"utc_offset":-25200.0,"location_city":null,"location_state":null,"location_country":null,"pr_count":6,"suffer_score":18,"has_heartrate":true,"average_heartrate":106.6,"max_heartrate":144,"average_cadence":null,"from_accepted_tag":false,"visibility":"everyone"}