{"id":14267721641,"achievement_count":0,"athlete":{"id":12343101,"resource_state":1},"athlete_count":1,"average_speed":3.821,"average_watts":128.0,"comment_count":0,"commute":false,"device_watts":false,"distance":17027.6,"elapsed_time":5045,"elev_high":281.8,"elev_low":35.4,"end_latlng":[37.98,-122.59],"external_id":"garmin_ping_432008427089","flagged":false,"gear_id":"b5121504","has_kudoed":false,"hide_from_home":null,"kilojoules":570.5,"kudos_count":4,"manual":false,"map":{"id":"a14267721641","polyline":null,"summary_polyline":"inxfF`lfkVr@Fx@UbBy@tHaCfAcAZ{BnEKrAv@fCr@lBvBxAhDx@jGn@dBnCfBxBx@hAbAH\\EVy@RMPs@~CFhAf@f@?PYf@i@TQV@RLFzAaAl@ECJw@XuAtBFRf@Rb@h@p@Hh@f@hAN\\A`Ac@~@F~@eB|@On@i@~@mB|BHZ_@t@sAb@QbAI|@l@n@z@x@G^Jb@p@Lh@bAjAS`Ct@`@V|@M~DNvBGr@g@zA?tAaApCGd@J\\v@~@|CfCFPQbAo@PITFxDPKf@kBt@YZiAj@}@pAeA\\mCb@gA|BL|CaBdD[hB{A^MlEi@~B{@fAGj@h@RlAr@pB|@f@\\l@\\VXGx@mAdC{@z@_AfIoT|DdJTbAdA~AHl@GdBb@pC]v@^q@e@gDFkB[}@k@q@Oo@Jk@XMX@b@`@n@pAVTfA[nABzBiAlAj@bB`@XGRs@Z[TId@P`AQb@gBt@CNYDg@l@Y`@m@ZG|AJbBMxAv@`A`Af@HvBGFm@I]aAM_@W{AyCj@wAp@WrAqBCWeAAcEjAgBv@w@Yw@h@k@Hk@OE}CLsBl@qDZoEb@wA@e@a@{A{@aAeA]cAtA{@vB{@r@m@bAq@Tc@^Ad@^d@Nt@e@rBkC`A_BJc@d@Qp@UJOhAThCKlAt@lB@`@[HSKMNLSPJXK|@bASl@_ARoAk@aAPe@GkD{BmB}Ba@@e@p@wHtSk@`AkCfAoAxAe@Cg@_Ay@g@oAkEa@]q@AqCbA{El@}BdByD`@yBrAy@Ju@Yc@Bi@bAc@`D}@j@w@lA[~@e@RY`@[nAHtAQxBOV_DWqAt@iBf@w@~@cB@eNqAkC{@gCuA_AIsAt@q@dAaB[yAZaBk@_@Ha@^C~Ay@Ne@n@UFQMSs@MaDNsBb@wBQqBJyBIeBy@cBiAsDk@cAqEsEc@]qAUaB}AwCSmCcAeA}As@g@{@M_BPo@Mm@}A}@y@q@sAcBcB[i@i@wAOgA[{@HgBO]{Ci@mEU_ByBiE_BkAoA_Bu@aAoBe@mBW]sGuC]_@I[r@}Nb@mDfAaE\\{BMWLg@QL?r@WfB}AnGa@bHNNdCLNPOrElFhCf@fA|@zCvEbDnAyA`GzElByA"},"max_speed":13.7,"max_watts":null,"moving_time":4456,"name":"Ring-necked snake season","photo_count":0,"private":false,"sport_type":"Ride","start_date":"2025-04-23T22:15:28Z","start_date_local":"2025-04-23T15:15:28Z","start_latlng":[37.98,-122.59],"timezone":"(GMT-08:00) America/Los_Angeles","total_elevation_gain":383.0,"total_photo_count":1,"trainer":false,"type":"Ride","upload_id":15225779354,"upload_id_str":"15225779354","weighted_average_watts":null,"workout_type":10,"utc_offset":-25200.0,"location_city":null,"location_state":null,"location_country":null,"pr_count":0,"suffer_score":22,"has_heartrate":true,"average_heartrate":114.6,"max_heartrate":142,"average_cadence":null,"from_accepted_tag":false,"visibility":"everyone"}