{"id":15880731177,"achievement_count":0,"athlete":{"id":12343101,"resource_state":1},"athlete_count":1,"average_speed":2.355,"average_watts":255.9,"comment_count":0,"commute":false,"device_watts":true,"distance":3734.7,"elapsed_time":1818,"elev_high":306.8,"elev_low":236.4,"end_latlng":[34.17,-118.13],"external_id":"garmin_ping_482433019199","flagged":false,"gear_id":"g24602749","has_kudoed":false,"hide_from_home":null,"kilojoules":405.1,"kudos_count":5,"manual":false,"map":{"id":"a15880731177","polyline":null,"summary_polyline":"ebkoEhz~oUeABWBG?{@FOAq@By@AcB@c@AOEe@F[Ag@B}A?o@A_A@SAk@D{@?wAD}@?uAH{@CUIgACkBDk@CQBQ?QEWDiAAqAFQCaA@e@CgCF_AKc@Aa@BcACMIc@FkB?GBg@?M?EEc@FEAiBBi@BQAU@KFO@u@Bq@Am@HkCA}@BqACEBiBCu@BaB?_A?e@CiADi@A[@k@Ak@Bs@Aa@H}@@o@D{@A]@SH[@mCCaABu@@u@CwCBg@AE@S@y@?EBAJBz@?tCa@BuAAs@Do@AG@MJINOBiAAgADQCeA?eDBS@MJIL?`@BnECzA@lDApA"},"max_speed":3.56,"max_watts":474,"moving_time":1586,"name":"Drop-off","photo_count":0,"private":false,"sport_type":"Run","start_date":"2025-09-20T20:32:03Z","start_date_local":"2025-09-20T13:32:03Z","start_latlng":[34.14,-118.13],"timezone":"(GMT-08:00) America/Los_Angeles","total_elevation_gain":63.0,"total_photo_count":0,"trainer":false,"type":"Run","upload_id":16959827276,"upload_id_str":"16959827276","weighted_average_watts":237,"workout_type":null,"utc_offset":-25200.0,"location_city":null,"location_state":null,"location_country":null,"pr_count":0,"suffer_score":49,"has_heartrate":true,"average_heartrate":150.3,"max_heartrate":163,"average_cadence":80.3,"from_accepted_tag":false,"visibility":"everyone"}