{"id":17256282056,"achievement_count":19,"athlete":{"id":12343101,"resource_state":1},"athlete_count":1,"average_speed":4.677,"average_watts":124.4,"comment_count":0,"commute":false,"device_watts":true,"distance":33742.1,"elapsed_time":8848,"elev_high":564.0,"elev_low":278.8,"end_latlng":[34.17,-118.14],"external_id":"garmin_ping_530562223846","flagged":false,"gear_id":"b8359472","has_kudoed":false,"hide_from_home":null,"kilojoules":894.4,"kudos_count":1,"manual":false,"map":{"id":"a17256282056","polyline":null,"summary_polyline":"gypoE`h`pUiCLCvJ{HVLtY{A\\LpZiKf@DhP~J\\FfIwCni@aBzQSdKaBdZLVnBFwBlA_BVu@nCbApDp@vIzBhMG`B}@tADhAtD|@hDP~DKFvk@YlAiHvNW`CJpA~BtHdAz@vAMhCoCvBgAv@BPx@Wb@eBf@aDjMqB~BInG}@dDu@z@kAVmCo@q@aAwAsFy@k@aA?u@h@Ur@@vCU~BoC~EUrD_AtAeAN{C}@yACgPpFyIOUd@\\nD_@hD^lEkBpCqBxAsArCkE_DaBkDkCAq@wBg@[gCzAE`AZjAq@zC_CaBaCs@cAvA_FlAc@~@G~Ae@`@aGTeAuB[G}BrCGjCw@hCEnAiCjACf@d@hAu@zDl@~ASfBzBdFjAfEQ|EgAvA`@fAjBy@zDn@vB_A`C^LyAiAoBGaCrBwBdGqBlAbBdAl@vCWtAj@~B`ChA|BvBDzBt@zACpDfBdCGhBlC~Cu@hDrAn@~Ce@zA\\fBK~Av@n@LvAt@rAOjA_AjA]lAJdBZBvBaARaB`@w@jCs@~@Xv@bA`EFz@tBxBMpBZfBYpA^bA]v@oBl@Ot@rAfBGfDz@zBi@lAxBjAl@fBM`AyA`AZlAaCJVc@tBDxA[|Aj@tDdB`C\\vAtBrBsBoB[sAuAeBa@yA]aC^}AI{@b@iCGc@uAfC_AY_AtA_BHoAe@mAyBwBd@kDy@oBF{@wAq@^k@`B{@ZiA]kBXoFKeAwBiBUu@To@QgBsAkCr@e@z@KxAmCdAW{A\\sA`AiAPwAs@qAMsAy@u@JqAWqB^yA[gC]g@yCgAcDv@eBiCmC@sC_BoFw@wBGeAuBiCmCqDo@pAeAp@wC?_DVaA^y@zBeB@w@}@qBPwAxAk@rBt@^SR}@O{Do@iAf@_D_CyAe@cA?e@~@gAFs@gAeB{ByEc@}B^I|BzA`AkDd@M~AfAvBtFd@H~Ak@CoDr@u@a@cCxAaBOaA_C{@iAkAeAaEMgCy@aBLkDeB}CZiGg@gC?{Cc@qDE_DaBeE~@sFSa@eBi@Qw@JgBzAiFjAoJhAoBnBqHhFkHrBkFQIsAzCoDqC`@eOd@_E|AaGbDkHt@qCP{BAkl@bAcKAkLImEq@yHo@yj@NgDzD_Np_@mhAWs@E}Y~Bm@CmWhBSP]Ag]lL]H{FtAgB?iThKd@nGM?i@{@QGuBD|Bx@N?\\aSc@YR@vS{AbCBr\\FzGbA~@B~e@xOTBz`@RVrCA"},"max_speed":12.14,"max_watts":512,"moving_time":7215,"name":"Lunch Ride","photo_count":0,"private":false,"sport_type":"Ride","start_date":"2026-02-01T19:15:48Z","start_date_local":"2026-02-01T11:15:48Z","start_latlng":[34.17,-118.14],"timezone":"(GMT-08:00) America/Los_Angeles","total_elevation_gain":711.0,"total_photo_count":0,"trainer":false,"type":"Ride","upload_id":18352220685,"upload_id_str":"18352220685","weighted_average_watts":153,"workout_type":null,"utc_offset":-28800.0,"location_city":null,"location_state":null,"location_country":null,"pr_count":10,"suffer_score":75,"has_heartrate":true,"average_heartrate":124.1,"max_heartrate":159,"average_cadence":80.9,"from_accepted_tag":false,"visibility":"everyone"}