{"id":17301668907,"achievement_count":2,"athlete":{"id":12343101,"resource_state":1},"athlete_count":1,"average_speed":4.956,"average_watts":142.4,"comment_count":0,"commute":true,"device_watts":true,"distance":10670.4,"elapsed_time":2371,"elev_high":476.8,"elev_low":236.6,"end_latlng":[34.17,-118.14],"external_id":"garmin_ping_532056434694","flagged":false,"gear_id":"b8359472","has_kudoed":false,"hide_from_home":null,"kilojoules":304.1,"kudos_count":1,"manual":false,"map":{"id":"a17301668907","polyline":null,"summary_polyline":"i_koExz~oUqE@gFDc@GoCFkC@sACgBDeA?mAESBQAaAF{BCyMDsACmADs@Ae@CcAAoAGqBAyA@{GZqB?GC_@HaE?}BDuCCcDBe@CaABwAAgCBw@A{FDqD?oDF[CkAB{AAkBBaDAqKBI@GFAH?rEGTGD_CBYB_BCeABkAC{A@y@Bo@AWB_AEg@BgB@_A?YCgADc@Ae@@YC_BDeCAYAu@@m@A{@BaA?WAuEBo@CyADeAAEBELDxCCdB@|AAt@ED{BAaCIs@?o@@gAEk@?wAGm@?YBUEoAEoLQiBEsBAwCIiEEiCIwII}AG{AAOCaBC[@gAEoB@aACe@Eg@@MC}@BsEMcA?sAES@m@?[EkA?QCcA@a@Ge@Bw@E_@B_@CW@OCQ@KCO@MEu@@IDCF?DJDzHF|JRhJLhFRJHNp@@NA\\G\\q@xAU`A?DBBV?TJBEK@IEW?_@SCG?QZyA@a@GIq@UAFF@HEl@VAZl@lAPLRBDDBJCn@@HFHH?HCDIn@gDFIJCJ@zR`HvFtB~FpBxHnCdDdAzB|@~FrBlDjAh@Rl@NNB~HEr@@jCApG?vACp@@n@E~D@hAAvFAJEHIBMEyIFKRG`CA"},"max_speed":14.24,"max_watts":638,"moving_time":2153,"name":"Afternoon Ride","photo_count":0,"private":false,"sport_type":"Ride","start_date":"2026-02-06T00:37:15Z","start_date_local":"2026-02-05T16:37:15Z","start_latlng":[34.14,-118.13],"timezone":"(GMT-08:00) America/Los_Angeles","total_elevation_gain":241.0,"total_photo_count":0,"trainer":false,"type":"Ride","upload_id":18397905665,"upload_id_str":"18397905665","weighted_average_watts":164,"workout_type":10,"utc_offset":-28800.0,"location_city":null,"location_state":null,"location_country":null,"pr_count":0,"suffer_score":25,"has_heartrate":true,"average_heartrate":125.1,"max_heartrate":152,"average_cadence":81.4,"from_accepted_tag":false,"visibility":"everyone"}