{"id":18206030757,"achievement_count":0,"athlete":{"id":12343101,"resource_state":1},"athlete_count":1,"average_speed":5.087,"average_watts":136.9,"comment_count":0,"commute":true,"device_watts":true,"distance":4410.8,"elapsed_time":1023,"elev_high":314.2,"elev_low":235.6,"end_latlng":[34.17,-118.14],"external_id":"garmin_ping_561676051536","flagged":false,"gear_id":"b8359472","has_kudoed":false,"hide_from_home":null,"kilojoules":117.1,"kudos_count":1,"manual":false,"map":{"id":"a18206030757","polyline":null,"summary_polyline":"y_koEzz~oUy@FQE]CSBmEAi@Dq@Cy@@[C_CD{E?i@DaECyKDmF?y@B_AC_CBg@EwAAYEaCC_B@iCJiABkAJgA?w@C]FS@wCAoOF}AA{GDkAAgFD_@CgA@oBB{@?[A}GD_@AoABk@CaABoB?y@B{ACo@@GBCHAr@@hDCRGBoAB}AAwCDi@Aa@CkB?uDHOFEFCHAd@@lDAJBpDAz@ENARCv@FfODJFDH@hC?"},"max_speed":9.72,"max_watts":681,"moving_time":867,"name":"Afternoon Ride","photo_count":0,"private":false,"sport_type":"Ride","start_date":"2026-04-22T00:51:06Z","start_date_local":"2026-04-21T17:51:06Z","start_latlng":[34.14,-118.13],"timezone":"(GMT-08:00) America/Los_Angeles","total_elevation_gain":78.0,"total_photo_count":0,"trainer":false,"type":"Ride","upload_id":19308704581,"upload_id_str":"19308704581","weighted_average_watts":146,"workout_type":10,"utc_offset":-25200.0,"location_city":null,"location_state":null,"location_country":null,"pr_count":0,"suffer_score":3,"has_heartrate":true,"average_heartrate":105.3,"max_heartrate":142,"average_cadence":80.8,"from_accepted_tag":false,"visibility":"everyone"}